jupyter_vscode_proxy/__init__.py
jupyter_vscode_proxy/icons/code-server.svg
jupyter_vscode_proxy/icons/vscode.svg
jupyter_vscode_proxy-0.6.dist-info/LICENSE
jupyter_vscode_proxy-0.6.dist-info/METADATA
jupyter_vscode_proxy-0.6.dist-info/WHEEL
jupyter_vscode_proxy-0.6.dist-info/entry_points.txt
jupyter_vscode_proxy-0.6.dist-info/top_level.txt
jupyter_vscode_proxy-0.6.dist-info/RECORD
