Metadata-Version: 2.1
Name: jupyter_vscode_proxy
Version: 0.6
Summary: VS Code extension for Jupyter
Author-email: Tim Head <noreply@example.com>
License: BSD-3-clause
Project-URL: repository, https://github.com/betatim/vscode-binder
Classifier: Programming Language :: Python :: 3
Classifier: Programming Language :: Python :: 3.8
Classifier: Programming Language :: Python :: 3.9
Classifier: Programming Language :: Python :: 3.10
Classifier: Programming Language :: Python :: 3.11
Requires-Python: >=3.8
License-File: LICENSE
